joy/__init__.py
joy/__main__.py
joy/defs.txt
joy/joy.py
joy/library.py
joy/parser.py
joy/utils/__init__.py
joy/utils/errors.py
joy/utils/generated_library.py
joy/utils/pretty_print.py
joy/utils/snippets.py
joy/utils/stack.py
Thun-0.5.1.dist-info/METADATA
Thun-0.5.1.dist-info/WHEEL
Thun-0.5.1.dist-info/top_level.txt
Thun-0.5.1.dist-info/RECORD
