Metadata-Version: 2.1
Name: Thun
Version: 0.5.1
Summary: Python Implementation of Joy
Home-page: https://joypy.osdn.io
Author: Simon Forman
Author-email: sforman@hushmail.com
License: GPLv3+
Platform: UNKNOWN
Classifier: Development Status :: 4 - Beta
Classifier: License :: OSI Approved :: GNU General Public License v3 or later (GPLv3+)
Classifier: Programming Language :: Python :: 3
Classifier: Programming Language :: Other
Classifier: Topic :: Software Development :: Interpreters
Provides-Extra: build-docs
Requires-Dist: sphinx ; extra == 'build-docs'
Requires-Dist: ipython ; extra == 'build-docs'
Requires-Dist: nbconvert ; extra == 'build-docs'
